notes2py/__init__.py
notes2py/__main__.py
notes2py/__version__.py
notes2py/ui/__init__.py
notes2py/ui/main.py
Notes2Py-0.3.4.dist-info/LICENSE
Notes2Py-0.3.4.dist-info/METADATA
Notes2Py-0.3.4.dist-info/WHEEL
Notes2Py-0.3.4.dist-info/entry_points.txt
Notes2Py-0.3.4.dist-info/top_level.txt
Notes2Py-0.3.4.dist-info/RECORD
