Metadata-Version: 2.1
Name: Notes2Py
Version: 0.3.4
Summary: PyQt app to manage your notes
Home-page: https://github.com/fast-geek/Notes2Py
Author: lav.
Author-email: me@lavn.ml
License: MIT
Project-URL: Homepage, https://github.com/fast-geek/Notes2Py
Keywords: python pyqt notes
Classifier: Programming Language :: Python :: 3
Classifier: License :: OSI Approved :: MIT License
Classifier: Operating System :: OS Independent
Requires-Python: >=3.6.1
License-File: LICENSE
Requires-Dist: PyQt6
Requires-Dist: tinydb
